randonautentropy/__init__.py
randonautentropy/cmd.py
randonautentropy/install.py
randonautentropy/rndo.py
randonautentropy/temporal.py
randonautentropy-1.0.4.dist-info/licenses/LICENSE
randonautentropy-1.0.4.dist-info/METADATA
randonautentropy-1.0.4.dist-info/WHEEL
randonautentropy-1.0.4.dist-info/entry_points.txt
randonautentropy-1.0.4.dist-info/top_level.txt
randonautentropy-1.0.4.dist-info/RECORD
