Metadata-Version: 2.4
Name: randonautentropy
Version: 1.0.4
Summary: Python API for interacting with The Randonautica Quantum Random Number Generator
Home-page: https://github.com/randogoth/randonautentropy
Author: randogoth
Author-email: randogoth@posteo.org
Classifier: Programming Language :: Python :: 3
Classifier: License :: OSI Approved :: MIT License
Classifier: Operating System :: OS Independent
Requires-Python: >=3.6
License-File: LICENSE
Requires-Dist: requests
Dynamic: author
Dynamic: author-email
Dynamic: classifier
Dynamic: description
Dynamic: description-content-type
Dynamic: home-page
Dynamic: license-file
Dynamic: requires-dist
Dynamic: requires-python
Dynamic: summary
